cubenet/__init__.py
cubenet/cubenet.py
cubenet-0.0.1.dist-info/METADATA
cubenet-0.0.1.dist-info/WHEEL
cubenet-0.0.1.dist-info/top_level.txt
cubenet-0.0.1.dist-info/RECORD
