Metadata-Version: 2.1
Name: cubenet
Version: 0.0.1
Summary: CubeNet工具集
Home-page: https://git.openi.org.cn/openi/cubenet
Author: cubeai
Author-email: cubeai@163.com
License: Apache License 2.0
Keywords: cubenet
Classifier: Development Status :: 4 - Beta
Classifier: Intended Audience :: Developers
Classifier: Intended Audience :: Science/Research
Classifier: Programming Language :: Python :: 3
Classifier: Programming Language :: Python :: 3.5
Classifier: Programming Language :: Python :: 3.6
Classifier: Programming Language :: Python :: 3.7
Classifier: Programming Language :: Python :: 3.8
Classifier: Programming Language :: Python :: 3.9
Classifier: License :: OSI Approved :: Apache Software License
Requires-Python: >=3.5
